img_compress/__init__.py
img_compress/compress.py
img_compress-0.0.3.dist-info/LICENSE
img_compress-0.0.3.dist-info/METADATA
img_compress-0.0.3.dist-info/WHEEL
img_compress-0.0.3.dist-info/top_level.txt
img_compress-0.0.3.dist-info/RECORD
